<?xml version="1.0" encoding="UTF-8"?>
<?xml-model href="../schema/identified-entities.rng" type="application/xml" schematypens="http://relaxng.org/ns/structure/1.0"?>
<person xmlns="http://www.tei-c.org/ns/1.0" xml:id="DCP-IDENT-2595" status="released">
    <persName>
        <forename>James</forename>
        <forename>Finlay</forename>
        <forename>Weir</forename>
        <surname>Johnston</surname>
    </persName>
    
    <note type="dates"><date>1796–1855</date></note>
    <sex value="M"/>
    <note type="biography">
        <p>Reader in chemistry and mineralogy, Durham University, 1833–55. Chemist to the Agricultural Society of Scotland, 1843. FRS 1837.</p></note>
    <note type="sources">
        <p><ref target="../bibliographies/bibl_1983.xml" resp="#mjhawkins">R. Desmond 1977</ref>, <ref target="../bibliographies/bibl_2063.xml" resp="#mjhawkins"><hi rend="italic">DNB</hi></ref>.</p>
    </note>
    <note type="volume">4</note>
    <note type="keywords">
        <term type="society">FRS</term>
        <term type="societal">Durham University</term>
        <term type="societal">Agricultural Society of Scotland </term>
        <term type="place">Durham</term>
        <term type="place">Scotland</term>
        <term type="a">Chemist</term>
        <term type="a">mineralogist</term>
    </note>
</person>