<?xml version="1.0" encoding="UTF-8"?>
<?xml-model href="../schema/identified-entities.rng" type="application/xml" schematypens="http://relaxng.org/ns/structure/1.0"?>
<person xmlns="http://www.tei-c.org/ns/1.0" xml:id="DCP-IDENT-5292" status="released">
    <persName>
        <forename>Nicola</forename>
        <surname>Zanichelli</surname>
    </persName>
    
    <note type="dates"><date>1819–84</date></note>
    
    <note type="biography">
        <p>Italian bookseller and publisher based in Modena and Bologna. Published the first Italian edition of <hi rend="italic">Origin.</hi></p></note>
    <note type="sources">
        <p><ref target="../bibliographies/bibl_2290.xml" resp="#mjhawkins"><hi rend="italic">EI</hi></ref></p>
        <p><ref target="../bibliographies/bibl_2661.xml" resp="#mjhawkins">Freeman 1977</ref>, p. 105</p>
    </note>
    <note type="volume">11,16,18, 23</note>
    <note type="keywords">
        <term type="language">Italian</term>
        <term type="place">Modena</term>
        <term type="place">Bologna</term>
        <term type="reference">Italian edition of Origin</term>
        <term type="nationality">Italian</term>
        <term type="c">bookseller</term>
        <term type="c">publisher</term>
    </note>
</person>