<?xml version="1.0" encoding="UTF-8"?>
<?xml-model href="../schema/identified-entities.rng" type="application/xml" schematypens="http://relaxng.org/ns/structure/1.0"?>
<person xmlns="http://www.tei-c.org/ns/1.0" xml:id="DCP-IDENT-8044" status="released">
    <persName>
        <forename>William</forename>
        <surname>Bodenhamer</surname>
    </persName>
    
    <note type="dates"><date>1808–1905</date></note>
    <sex value="M"/>
    <note type="biography">
        <p>American physician. MD, Ohio, 1839. Settled in New York in 1859. A specialist in rectal diseases. Author of <hi rend="italic">A practical treatise on the aetiology, pathology and treatment of congenital malformations of the rectum and anus</hi> (1860).</p></note>
    <note type="sources">
        <p><ref target="../bibliographies/bibl_148.xml" resp="#mjhawkins"><hi rend="italic">American medical biography</hi></ref></p>
    </note>
    <note type="volume">25</note>
    <note type="keywords">
        <term type="occupation">Physician</term>
    </note>
</person>