<?xml version="1.0" encoding="UTF-8"?>
<?xml-model href="../schema/identified-entities.rng" type="application/xml" schematypens="http://relaxng.org/ns/structure/1.0"?>
<person xmlns="http://www.tei-c.org/ns/1.0" xml:id="DCP-IDENT-7267" status="released">
    <persName>
        <forename>William</forename>
        <surname>Carr</surname>
    </persName>
    
    <note type="dates"><date>1822–75</date></note>
    <sex value="M"/>
    <note type="biography">
        <p>Landowner and solicitor. Author of a work on shorthorn cattle.</p></note>
    <note type="sources">
        <p><ref target="../bibliographies/bibl_9153.xml" resp="#mjhawkins"><hi rend="italic">BMD</hi></ref> (<hi rend="italic">Death index</hi>)</p>
        <p><ref target="../bibliographies/bibl_1279.xml" resp="#mjhawkins">Carr 1867</ref></p>
        <p>Census returns of England and Wales 1851 (The National Archives: Public Record Office HO107/1591/515/19), 1861 (RG9/3178/62/28)</p>
    </note>
    <note type="volume">22</note>
</person>