<?xml version="1.0" encoding="UTF-8"?>
<?xml-model href="../schema/identified-entities.rng" type="application/xml" schematypens="http://relaxng.org/ns/structure/1.0"?>
<person xmlns="http://www.tei-c.org/ns/1.0" xml:id="DCP-IDENT-1570" status="released">
    <persName>
        <forename>Thomas</forename>
        <forename>Campbell</forename>
        <surname>Eyton</surname>
    </persName>
    
    <note type="dates"><date>1809–80</date></note>
    <sex value="M"/>
    <note type="biography">
        <p>Shropshire naturalist. Friend and Cambridge contemporary of CD. Author of several works on natural history. On coming into possession of the family estate at Eyton, Shropshire, in 1855, he built a museum for which he formed a collection of skins and skeletons of European birds. A magistrate throughout his adult life.</p></note>
    <note type="sources">
        <p><ref target="../bibliographies/bibl_5933.xml" resp="#mjhawkins"><hi rend="italic">ODNB</hi></ref>.</p>
    </note>
    <note type="volume">1,2,4,5,6,7,8,9,10,12,13,15,16,17,18,19,20,22,24,27</note>
    <note type="keywords">
        <term type="name">Darwin, C. R.</term>
        <term type="fauna">birds</term>
        <term type="societal">museum</term>
        <term type="place">Cambridge</term>
        <term type="place">Eyton</term>
        <term type="place">Shropshire</term>
        <term type="place">Europe</term>
        <term type="reference">works on natural history</term>
        <term type="nationality">Shropshire</term>
        <term type="a">naturalist</term>
    </note>
</person>