<?xml version="1.0" encoding="UTF-8"?>
<?xml-model href="../schema/identified-entities.rng" type="application/xml" schematypens="http://relaxng.org/ns/structure/1.0"?>
<person xmlns="http://www.tei-c.org/ns/1.0" xml:id="DCP-IDENT-8743" status="released">
    <persName>
        <forename>Matilda</forename>       
        <choice><seg><surname notBefore="1815" notAfter="1847">Rigby</surname></seg>
            <seg><surname notBefore="1847" notAfter="1890">Smith</surname></seg></choice>
    </persName>     
    <note type="dates"><date>1815–90</date></note>
    <sex value="F"/>
    <note type="biography">
        <p>Indexer. Worked for John Murray. Daughter of Anne Palgrave and Edward Rigby. Cousin of Maria Turner, Joseph Dalton Hooker’s mother. Married James Smith (1808–71), an East India merchant, in 1847. Mother of Matilda Smith (1854–1926), the botanical artist. Indexed <hi rend="italic">Cross and self fertilisation</hi>, <hi rend="italic">Forms of flowers</hi>, and <hi rend="italic">Movement in plants</hi>.</p>
    </note>
    <note type="sources">
        <p>Census returns of England and Wales 1861 (The National Archives: Public Record Office RG/9/2686/95/37)</p>
        <p><hi rend="italic">England &amp; Wales, national probate calendar</hi> (<hi rend="italic">index of wills and administrations</hi>), <hi rend="italic">1858–1966, 1973–95</hi> (Ancestry.com, accessed 3 April 2019)</p>
        <p><hi rend="italic">England, select births and christenings, 1538–1975</hi> (Ancestry.com, accessed 3 April 2019)</p>
        <p>letters from Matilda Smith to John Murray, 27 October 1876, 16 June 1877 (National Library of Scotland, John Murray Archive (family papers)) and John Murray copies ledger (National Library of Scotland, John Murray Archive &amp; Publishers’ Collections, MS.42733)</p>
    <p><hi rend="italic">Scotland, select marriages, 1561–1910</hi>  (Ancestry.com, accessed 3 April 2019)</p>
        </note>
    <note type="volume">28</note>
    
   
</person>