<?xml version="1.0" encoding="UTF-8"?>
<?xml-model href="../schema/identified-entities.rng" type="application/xml" schematypens="http://relaxng.org/ns/structure/1.0"?>
<person xmlns="http://www.tei-c.org/ns/1.0" xml:id="DCP-IDENT-1919" status="released" n="a">
    <persName>
        <forename>George</forename>
        <surname>Gordon</surname>
    </persName>
    
    <note type="dates"><date>1801–93</date></note>
    <sex value="M"/>
    <note type="biography">
        <p>Scottish botanist, geologist, and clergyman. Minister of Birnie, near Elgin, Morayshire, 1832–89. Specialised in the stratigraphy and fossil vertebrates of Elgin sandstone. Founded the Elgin and Morayshire Literary and Scientific Association.</p></note>
    <note type="sources">
        <p><ref target="../bibliographies/bibl_1985.xml" resp="#mjhawkins">R. Desmond 1994</ref></p>
        <p><ref target="../bibliographies/bibl_6895.xml" resp="#mjhawkins">Sarjeant 1980–96</ref>.</p>
    </note>
    <note type="volume">11,13,29</note>
    <note type="keywords">
        <term type="fauna">vertebrates</term>
        <term type="societal">Elgin and Morayshire Literary and Scientific Association </term>
        <term type="place">Birnie</term>
        <term type="place">Elgin</term>
        <term type="place">Morayshire</term>
        <term type="geological">stratigraphy</term>
        <term type="geological">sandstone</term>
        <term type="nationality">Scottish</term>
        <term type="a">botanist</term>
        <term type="a">geologist</term>
        <term type="p">clergyman</term>
    </note>
</person>