<?xml version="1.0" encoding="UTF-8"?>
<?xml-model href="../schema/identified-entities.rng" type="application/xml" schematypens="http://relaxng.org/ns/structure/1.0"?>
<person xmlns="http://www.tei-c.org/ns/1.0" xml:id="DCP-IDENT-6610" status="released">
    <persName>
        <forename>Hannah</forename>
        <choice>
            <seg><surname notBefore="1768" notAfter="1789">Ball</surname></seg>
            <seg><surname notBefore="1789" notAfter="1822">Reynolds</surname></seg>
        </choice>
    </persName>
    
    <note type="dates"><date>1768–1822</date></note>
    <sex value="F"/>
    <note type="biography">
        <p>Daughter of Joseph and Susannah Ball; her mother was a sister of Richard Reynolds. Married at Bridgewater, Somerset, her cousin, Richard Reynold’s son, William, an ironfounder at Ketley, Shropshire, in 1789. Mother of Susanna Hannah Reynolds. Moved to Broseley, Shropshire, but returned to Ketley after her husband’s death in 1803.</p></note>
    <note type="sources">
        <p><hi rend="italic">Bristol, England, non-conformist baptism, marriage and burial registers, 1644–1981</hi> (Ancestry.com, accessed 28 April 2022)</p>
        <p><ref target="../bibliographies/bibl_1581.xml"><hi rend="italic">Correspondence</hi></ref> vol. 13, Supplement, letter to Dear Friend, 12 January 1822</p>
        <p><ref target="../bibliographies/bibl_5933.xml"><hi rend="italic">ODNB</hi></ref> s.v. Reynolds, William</p>
        <p><ref target="../bibliographies/bibl_7888.xml"><hi rend="italic">Two Shropshire ironmasters</hi></ref></p>
    </note>
    <note type="volume">13</note>
</person>