<?xml version="1.0" encoding="UTF-8"?>
<?xml-model href="../schema/identified-entities.rng" type="application/xml" schematypens="http://relaxng.org/ns/structure/1.0"?>
<person xmlns="http://www.tei-c.org/ns/1.0" xml:id="DCP-IDENT-3660" status="released">
    <persName>
        <forename>William</forename>
        <surname>Pamplin</surname>
    </persName>
    
    <note type="dates"><date>1806–99</date></note>
    <sex value="M"/>
    <note type="biography">
        <p>Botanist, bookseller, and publisher. Son of the nurseryman William Pamplin (1768–1844; R. Desmond 1994); assisted his father until 1839. Botanical bookseller in Soho, London, 1839–62. Retired to Wales and tried to establish the North Wales Central Botanic Gardens. Published the <hi rend="italic">Phytologist</hi>, 1855–63. Associate of the Linnean Society of London, 1830. Member of the Botanical Society of London.</p></note>
    <note type="sources">
        <p><ref target="../bibliographies/bibl_1985.xml" resp="#mjhawkins">R. Desmond 1994</ref></p>
            <p><ref target="../bibliographies/bibl_5514.xml" resp="#mjhawkins"><hi rend="italic">Modern English biography</hi></ref>.</p>
    </note>
    <note type="volume">7,10,13,30</note>
    <note type="keywords">
        <term type="society">Associate</term>
        <term type="society">Member</term>
        <term type="name">nurseryman</term>
        <term type="name">William Pamplin</term>
        <term type="name">Desmond, Ray</term>
        <term type="societal">North Wales Central Botanic Gardens </term>
        <term type="societal">Linnean Society</term>
        <term type="societal">Botanical Society</term>
        <term type="place">Soho</term>
        <term type="place">London</term>
        <term type="place">Wales</term>
        <term type="place">North Wales</term>
        <term type="reference">Desmond, Ray 1994</term>
        <term type="reference">Phytologist</term>
        <term type="a">Botanist</term>
        <term type="c">bookseller</term>
        <term type="c">publisher</term>
    </note>
</person>