<?xml version="1.0" encoding="UTF-8"?>
<?xml-model href="../schema/identified-entities.rng" type="application/xml" schematypens="http://relaxng.org/ns/structure/1.0"?>
<person xmlns="http://www.tei-c.org/ns/1.0" xml:id="DCP-IDENT-1984" status="released">
    <persName>
        <forename>George</forename>
        <surname>Grey</surname>
    </persName>
    
    <note type="dates"><date>1812–98</date></note>
    <sex value="M"/>
    <note type="biography">
        <p>Army officer, explorer, and colonial governor. Governor of South Australia, 1841–5; of New Zealand, 1845–53 and 1861–8; of Cape Colony, 1854–61. Settled in New Zealand, 1870–94. Prime minister of New Zealand, 1877–9. Knighted, 1848.</p></note>
    <note type="sources">
        <p><ref target="../bibliographies/bibl_256.xml" resp="#mjhawkins"><hi rend="italic">Aust. dict. biog</hi></ref>.</p>
        <p><ref target="../bibliographies/bibl_5933.xml" resp="#mjhawkins"><hi rend="italic">ODNB</hi></ref>.</p>
    </note>
    <note type="volume">2,3,4,5,8,10,12,17,25</note>
    <note type="keywords">
        <term type="place">South Australia</term>
        <term type="place">New Zealand</term>
        <term type="place">Cape Colony</term>
        <term type="m">Army officer</term>
        <term type="z">explorer</term>
        <term type="p">colonial governor</term>
    </note>
</person>