<?xml version="1.0" encoding="UTF-8"?>
<?xml-model href="../schema/identified-entities.rng" type="application/xml" schematypens="http://relaxng.org/ns/structure/1.0"?>
<person xmlns="http://www.tei-c.org/ns/1.0" xml:id="DCP-IDENT-725" status="released">
    <persName>
        <forename>Christian</forename>
        <forename>Karl</forename>
        <forename>Josias</forename>
        <surname>Bunsen</surname>
    </persName>
    <persName type="additional" subtype="title">Freiherr von Bunsen</persName>
    
    <note type="dates"><date>1791–1860</date></note>
    <sex value="M"/>
    <note type="biography">
        <p>Prussian diplomat and scholar. Ambassador in London, 1841.</p></note>
    <note type="sources">
        <p><ref target="../bibliographies/bibl_2248.xml" resp="#mjhawkins"><hi rend="italic">EB</hi></ref></p>
        <p><ref target="../bibliographies/bibl_5820.xml" resp="#mjhawkins"><hi rend="italic">NDB</hi></ref>.</p>
    </note>
    <note type="volume">3,4,5</note>
    <note type="keywords">
        <term type="place">London</term>
        <term type="nationality">Prussian</term>
        <term type="p">diplomat</term>
        <term type="a">scholar</term>
    </note>
</person>