<?xml version="1.0" encoding="UTF-8"?>
<?xml-model href="../schema/identified-entities.rng" type="application/xml" schematypens="http://relaxng.org/ns/structure/1.0"?>
<person xmlns="http://www.tei-c.org/ns/1.0" xml:id="DCP-IDENT-3922" status="released">
    <persName>
        <forename>Andrew</forename>
        <forename>Crombie</forename>
        <surname>Ramsay</surname>
    </persName>
    
    <note type="dates"><date>1814–91</date></note>
    <sex value="M"/>
    <note type="biography">
        <p>Geologist. Appointed to the Geological Survey of Great Britain, 1841; senior director for England and Wales, 1862; director-general, 1872–81. Professor of geology, University College, London, 1847–52; lecturer on geology at the Royal School of Mines, 1852–71. President of the Geological Society of London, 1862–4. Knighted, 1881. FRS 1862.</p></note>
    <note type="sources">
        <p><ref target="../bibliographies/bibl_2160.xml" resp="#mjhawkins"><hi rend="italic">DSB</hi></ref></p>
        <p><ref target="../bibliographies/bibl_5933.xml" resp="#mjhawkins"><hi rend="italic">ODNB</hi></ref>.</p>
    </note>
    <note type="volume">3,4,5,6,7,8,9,10,11,12,13,14,16,17,19,20,22,23,24,25,26,28,29,30</note>
    <note type="keywords">
        <term type="society">FRS</term>
        <term type="societal">Geological Survey</term>
        <term type="societal">University College, London</term>
        <term type="societal">Royal School of Mines</term>
        <term type="societal">Geological Society</term>
        <term type="place">Great Britain</term>
        <term type="place">England</term>
        <term type="place">Wales</term>
        <term type="place">London</term>
        <term type="a">Geologist</term>
    </note>
</person>