<?xml version="1.0" encoding="UTF-8"?>
<?xml-model href="../schema/identified-entities.rng" type="application/xml" schematypens="http://relaxng.org/ns/structure/1.0"?>
<person xmlns="http://www.tei-c.org/ns/1.0" xml:id="DCP-IDENT-5694" status="released">
    <persName>
        <forename>Helen</forename>
        <choice>
            <seg><surname notBefore="1794" notAfter="1824">MacDowall</surname></seg>
            <seg><surname notBefore="1824" notAfter="1875">François de Chaumont</surname></seg>
        </choice>
    </persName>
    
    <note type="dates"><date>1794–1875</date></note>
    <sex value="F"/>
    <note type="biography">
        <p>Scottish. Natural daughter of Margaret (Peggy) Kennedy of Killochan, Dailly, Ayrshire, and Andrew McDouall of Logan MP. Married Louis François de Chaumont in Paris in 1824. Mother of Francis Stephen Bennet François de Chaumont.</p></note>
    <note type="sources">
        <p><ref target="../bibliographies/bibl_9153.xml" resp="#mjhawkins"><hi rend="italic">BMD</hi></ref> (<hi rend="italic">Death index</hi>)</p>
        <p>Census returns of Scotland 1861 (The National Archives of Scotland: St George 5/11/12) </p>
        <p><ref target="../bibliographies/bibl_1581.xml" resp="#mjhawkins"><hi rend="italic">Correspondence</hi></ref> vol. 19, letter from F. S. B. F. de Chaumont to W. E. Darwin, 11 March 1871</p>
        <p>Foreign registers and returns (The National Archives: Public Record Office RG33/63)</p>
        <p><ref target="../bibliographies/bibl_9820.xml">Namier and Brooke 1985</ref> s.v. McDouall, Andrew.</p>
    </note>
    <note type="volume">19,22</note>
    
</person>