<?xml version="1.0" encoding="UTF-8"?>
<?xml-model href="../schema/identified-entities.rng" type="application/xml" schematypens="http://relaxng.org/ns/structure/1.0"?>
<person xmlns="http://www.tei-c.org/ns/1.0" xml:id="DCP-IDENT-2814" status="released">
    <persName>
        <forename>Edwin</forename>
        <forename>Ray</forename>
        <surname>Lankester</surname>
    </persName>
    
    <note type="dates"><date>1847–1929</date></note>
    <sex value="M"/>
    <note type="biography">
        <p>Zoologist. Studied natural sciences at Oxford under George Rolleston, 1866–8; physiology at Leipzig and Vienna; morphology under Ernst Haeckel at Jena; marine zoology with Anton Dohrn in Naples, 1871–2. Fellow and tutor, Exeter College, Oxford, 1872–5; professor of zoology, University College, London, 1875–91; Linacre Professor of comparative anatomy, Oxford, 1891–8; director of the natural history departments and keeper of zoology, British Museum, 1898–1907. Knighted, 1907. FRS 1875.</p></note>
    <note type="sources">
        <p><ref target="../bibliographies/bibl_5933.xml" resp="#mjhawkins"><hi rend="italic">ODNB</hi></ref>.</p>
    </note>
    <note type="volume">17,18,19,20,21,22,23,24,25,26,27,28,29,30</note>
    <note type="keywords">
        <term type="society">FRS</term>
        <term type="name">Lankester, Edwin</term>
        <term type="societal">University College, London</term>
        <term type="place">London</term>
        <term type="a">Zoologist</term>
    </note>
</person>