<?xml version="1.0" encoding="UTF-8"?>
<?xml-model href="../schema/identified-entities.rng" type="application/xml" schematypens="http://relaxng.org/ns/structure/1.0"?>
<person xmlns="http://www.tei-c.org/ns/1.0" xml:id="DCP-IDENT-4004" status="released">
    <persName>
        <forename>Henry</forename>
        <forename>Nicholas</forename>
        <surname>Ridley</surname>
    </persName>
    
    <note type="dates"><date>1855–1956</date></note>
    <sex value="M"/>
    <note type="biography">
        <p>Economic botanist. BA, natural science, Oxford (Exeter College), 1878. Employed in the botanical department, British Museum, 1880. Participated in an expedition to Brazil sponsored by the Royal Society of London, 1887. Director, botanical gardens, Singapore, 1888. Travelled in the Malay Peninsula as well as Borneo, Burma, India, Egypt, Java, and Jamaica. Helped to establish the rubber plantation industry in Malaya. Founder and editor, <hi rend="italic">Agricultural Bulletin of the Straits and Federated Malay States</hi>, 1901. FRS 1907.</p></note>
    <note type="sources">
        <p><hi rend="italic">Agricultural Bulletin of the Straits and Federated Malay States</hi> n.s. 1 (1901): i</p>
        <p><ref target="../bibliographies/bibl_5933.xml" resp="#mjhawkins"><hi rend="italic">ODNB</hi></ref></p>
    </note>
    <note type="volume">25,26</note>
    <note type="keywords">
        <term type="society">FRS</term>
        <term type="flora">rubber plants</term>
        <term type="place">Malaya</term>
        <term type="a">Botanist</term>
    </note>
</person>