<?xml version="1.0" encoding="UTF-8"?>
<?xml-model href="../schema/identified-entities.rng" type="application/xml" schematypens="http://relaxng.org/ns/structure/1.0"?>
<person xmlns="http://www.tei-c.org/ns/1.0" xml:id="DCP-IDENT-5395" status="released">
    <persName>
        <forename>Henrietta</forename>
        <forename>Antonia</forename>
        <surname>Clive</surname>
    </persName>
    <persName type="additional" subtype="title">countess of Powis</persName>
    
    <note type="dates"><date>1758–1830</date></note>
    <sex value="F"/>
    <note type="biography">
        <p>Heiress of the last Herbert earl of Powis. Married Edward Clive in 1784.</p></note>
    <note type="sources">
            <p><ref target="../bibliographies/bibl_5933.xml" resp="#mjhawkins"><hi rend="italic">ODNB</hi></ref> s.v. Clive, Edward.</p>
    </note>
    <note type="volume">13</note>
    
</person>