<?xml version="1.0" encoding="UTF-8"?>
<?xml-model href="../schema/identified-entities.rng" type="application/xml" schematypens="http://relaxng.org/ns/structure/1.0"?>
<person xmlns="http://www.tei-c.org/ns/1.0" xml:id="DCP-IDENT-5466" status="released">
    <persName>
        <forename>Courtney</forename>
        <surname>Cresy</surname>
    </persName>
    
    <note type="dates"><date>1859–1929</date></note>
    <sex value="M"/>
    <note type="biography">
        <p>Paper maker. Son of Theodore Grant Cresy.</p></note>
    <note type="sources">
        <p><ref target="../bibliographies/bibl_9153.xml" resp="#mjhawkins"><hi rend="italic">BMD</hi></ref> (<hi rend="italic">Birth index</hi>)</p>
            <p>Census returns of England and Wales 1881 (The National Archives: Public Record Office RG11/872/68/23)</p>
        <p><hi rend="italic">England &amp; Wales, national probate calendar</hi> (<hi rend="italic">index of wills and administrations</hi>), <hi rend="italic">1858–1995</hi> (Ancestry.com, accessed 2 June 2020)</p>
    </note>
    <note type="volume">19</note>
    
</person>