<?xml version="1.0" encoding="UTF-8"?>
<?xml-model href="../schema/identified-entities.rng" type="application/xml" schematypens="http://relaxng.org/ns/structure/1.0"?>
<person xmlns="http://www.tei-c.org/ns/1.0" xml:id="DCP-IDENT-9331" status="released">
    <persName>
        <forename>Carl</forename>
        <surname>Fisch</surname>
    </persName>   
    <note type="dates"><date>1859–1913</date></note>
    <sex value="M"/>
    <note type="biography">
        <p>German botanist and zoologist. Studied at Rostock, Würzburg and Straßburg (Strasbourg); PhD, Straßburg, 1880. Privat-dozent, Erlangen, 1881–6. Emigrated to the United States, 1888. MD, St Louis, 1893. Naturalised American citizen, 1898. Practised in St Louis.</p>
    </note>
    <note type="sources">
        <p><ref target="../bibliographies/bibl_11657.xml">Leonard ed. 1906</ref></p>
        <p><hi rend="italic">Missouri death certificates, 1910–69</hi> (Ancestry.com, accessed 28 May 2021)</p>       
        <p><hi rend="italic">Sitzungsberichte der physikalisch-medizinischen Societät zu Erlangen</hi> (1886): VI</p>
        <p>United States Federal Census 1900 (Ward 24, St Louis City, Missouri 0358/6), 1910 (Ward 17, Saint Louis City, Missouri 0266/p. 8B) (Ancestry.com, accessed 28 May 2021)</p>
        <p><hi rend="italic">Verhandlungen des botanischen Vereins der Provinz Brandenburg</hi> 1880, p. XLVII</p>
    </note>
    <note type="volume">29</note>
    
   
</person>