<?xml version="1.0" encoding="UTF-8"?>
<?xml-model href="../schema/identified-entities.rng" type="application/xml" schematypens="http://relaxng.org/ns/structure/1.0"?>
<person xmlns="http://www.tei-c.org/ns/1.0" xml:id="DCP-IDENT-1528" status="released">
    <persName>
        <forename>Henry</forename>
        <forename>Napier</forename>
        <forename>Bruce</forename>
        <surname>Erskine</surname>
    </persName>
    
    <note type="dates"><date>1831–93</date></note>
    <sex value="M"/>
    <note type="biography">
        <p>Civil servant in India. Arrived in Bombay in 1853; sub-collector, Ahmadnagar and Shollapoor, 1868; collector and magistrate, Nasik, 1869; commissioner, northern division of Bombay, 1877–9; Sind, 1879–87. Son of Maitland and William Erskine.</p></note>
    <note type="sources">
        <p><ref target="../bibliographies/bibl_5933.xml" resp="#mjhawkins"><hi rend="italic">ODNB</hi></ref> s.v. Erskine, William (1773–1852), <ref target="../bibliographies/bibl_4094.xml" resp="#mjhawkins"><hi rend="italic">India list</hi></ref></p>
        <p><ref target="../bibliographies/bibl_5514.xml" resp="#mjhawkins"><hi rend="italic">Modern English biography</hi></ref>.</p>
    </note>
    <note type="volume">15,16</note>
    <note type="keywords">
        <term type="name">Erskine, C. J.</term>
        <term type="place">India</term>
        <term type="p">Civil servant</term>
    </note>
</person>