<?xml version="1.0" encoding="UTF-8"?>
<?xml-model href="../schema/identified-entities.rng" type="application/xml" schematypens="http://relaxng.org/ns/structure/1.0"?>
<person xmlns="http://www.tei-c.org/ns/1.0" xml:id="DCP-IDENT-2042" status="released">
    <persName>
        <forename>William</forename>
        <forename>Mackmurdo</forename>
        <surname>Hacon</surname>
    </persName>
    
    <note type="dates"><date>1821–85</date></note>
    <sex value="M"/>
    <note type="biography">
        <p>CD’s solicitor. Offices at 31 Fenchurch Street, London. Solicitor, 1854–85; formed partnerships with David Rowland, James Weston, and Edward Francis Turner at Leadenhall House, Leadenhall Street. Commissioner of oaths and affidavits, and examiner of witnesses in England, and for the High Court of Judicature, Bombay.</p></note>
    <note type="sources">
        <p><ref target="../bibliographies/bibl_9153.xml" resp="#mjhawkins"><hi rend="italic">BMD</hi></ref> (<hi rend="italic">Death index</hi>)</p>
        <p><hi rend="italic">England &amp; Wales, non-conformist and non-parochial registers, 1567–1970</hi> (Ancestry.com, accessed 30 January 2014)</p>
        <p><ref target="../bibliographies/bibl_4613.xml" resp="#mjhawkins"><hi rend="italic">Law list</hi></ref> 1854–85</p>
    </note>
    <note type="volume">11,12,16,19,22,24,25,26,27,29,30</note>
    <note type="keywords">
        <term type="c">Solicitor</term>
        <term type="name">Darwin, C. R.</term>
        <term type="name">Rowland, David</term>
        <term type="name">Weston, James</term>
        <term type="name">Turner, E. F.</term>
        <term type="societal">High Court of Judicature</term>
        <term type="place">Fenchurch Street</term>
        <term type="place">London</term>
        <term type="place">Leadenhall Street</term>
        <term type="place">England</term>
        <term type="place">Bombay</term>
    </note>
</person>