<?xml version="1.0" encoding="UTF-8"?>
<?xml-model href="../schema/identified-entities.rng" type="application/xml" schematypens="http://relaxng.org/ns/structure/1.0"?>
<person xmlns="http://www.tei-c.org/ns/1.0" xml:id="DCP-IDENT-5018" status="released">
    <persName>
        <forename>Hope</forename>
        <forename>Elizabeth</forename>
        <surname>Wedgwood</surname>
    </persName>
    <persName type="additional" subtype="nickname" resp="#mjhawkins">Dot</persName>
    
    <note type="dates"><date>1844–1935</date></note>
    <sex value="F"/>
    <note type="biography">
        <p>Daughter of Hensleigh and Frances Emma Elizabeth Wedgwood. Married as his second wife Godfrey Wedgwood in 1876.</p></note>
    <note type="sources">
        <p><ref target="../bibliographies/bibl_2662.xml" resp="#mjhawkins">Freeman 1978</ref></p>
        <p><ref target="../bibliographies/bibl_8245.xml">Wedgwood and Wedgwood 1980</ref>, pp. 310–11</p>
    </note>
    <note type="volume">7,9,11,12,13,15,19,20,21,22,23,24,WSL,27,29</note>
    <note type="keywords">
        <term type="name">Wedgwood, Hensleigh</term>
        <term type="name">Wedgwood, F. E. E.</term>
        <term type="name">Wedgwood, Godfrey</term>
    </note>
</person>