<?xml version="1.0" encoding="UTF-8"?>
<?xml-model href="../schema/identified-entities.rng" type="application/xml" schematypens="http://relaxng.org/ns/structure/1.0"?>
<person xmlns="http://www.tei-c.org/ns/1.0" xml:id="DCP-IDENT-8181" status="released">
    <persName>
        <forename>Henry</forename>
        <forename>Edward</forename>
        <surname>McCallum</surname>
    </persName>
    
    <note type="dates"><date>1852–1919</date></note>
    <sex value="M"/>
    <note type="biography">
        <p>Colonial administrator. Captain in the Royal Engineers, 1881. Governor of Lagos, 1897–9; Newfoundland, 1898–1901; Natal, 1901–7; Ceylon (Sri Lanka), 1907–13. Married Blanche Lily Julia Johnson in 1874.</p></note>
    <note type="sources">
        <p><ref target="../bibliographies/bibl_9153.xml" resp="#mjhawkins"><hi rend="italic">BMD</hi></ref> (<hi rend="italic">Birth index, Marriage index, Death index</hi>)</p>
        <p><ref target="../bibliographies/bibl_5933.xml" resp="#mjhawkins"><hi rend="italic">ODNB</hi></ref> s.v. Colonial administrators and post-independence leaders in Sri Lanka (1798–2000)</p> 
        <p><ref target="../bibliographies/bibl_5933.xml" resp="#mjhawkins"><hi rend="italic">ODNB</hi></ref> s.v. Colonial administrators and post-independence leaders in South Africa (1797–2000)</p>  
        <p><ref target="../bibliographies/bibl_5933.xml" resp="#mjhawkins"><hi rend="italic">ODNB</hi></ref> s.v. Colonial administrators and post-independence leaders in Canada (1710–2000)</p> 
        <p><ref target="../bibliographies/bibl_5933.xml" resp="#mjhawkins"><hi rend="italic">ODNB</hi></ref> s.v. Colonial administrators and post-independence leaders in Nigeria (1886–2000)</p> 
    </note>
    <note type="volume">25</note>
</person>