<?xml version="1.0" encoding="UTF-8"?>
<?xml-model href="../schema/identified-entities.rng" type="application/xml" schematypens="http://relaxng.org/ns/structure/1.0"?>
<person xmlns="http://www.tei-c.org/ns/1.0" xml:id="DCP-IDENT-8734" status="released">
    <persName>
        <forename>Arthur</forename>
        <surname>Achard</surname>
    </persName>     
    <note type="dates"><date>1836–1931</date></note>
    <sex value="M"/>
    <note type="biography">
        <p>Swiss engineer. Studied at the École des mines, Paris, 1858–61. Member of the Société de physique et d’histoire naturelle de Genève from 1865. Taught thermodynamics at the École spéciale, Lausanne. Worked in Paris for the Comptoir d’escompte de Genève, 1886–97.</p>
    </note>
    <note type="sources">
        <p><hi rend="italic">Historisches Lexikon der Schweiz</hi></p>
        <p><hi rend="italic">Memoires de la Société de physique et d’histoire naturelle de Genève</hi> (1911)</p>
    </note>
    <note type="volume">28</note>
     
    
    
</person>