<?xml version="1.0" encoding="UTF-8"?>
<?xml-model href="../schema/identified-entities.rng" type="application/xml" schematypens="http://relaxng.org/ns/structure/1.0"?>
<person xmlns="http://www.tei-c.org/ns/1.0" xml:id="DCP-IDENT-6583" status="released">
    <persName>
        <forename>Nicolas</forename>
        <forename>Willem</forename>
        <forename>Pieter</forename>
        <surname>Rauwenhoff</surname>
    </persName>
    
    <note type="dates"><date>1826–1909</date></note>
    
    <note type="biography">
        <p>Dutch botanist. Lecturer at the medical college of Rotterdam and high school teacher, 1860–71; professor of botany and director of the Utrecht botanical garden, 1871–96.</p></note>
    <note type="sources">
        <p><ref target="../bibliographies/bibl_7626.xml" resp="#mjhawkins"><hi rend="italic">Taxonomic literature</hi></ref>.</p>
    </note>
    <note type="volume">14</note>
</person>