<?xml version="1.0" encoding="UTF-8"?>
<?xml-model href="../schema/identified-entities.rng" type="application/xml" schematypens="http://relaxng.org/ns/structure/1.0"?>
<person xmlns="http://www.tei-c.org/ns/1.0" xml:id="DCP-IDENT-4369" status="released">
    <persName>
        <forename>Andrew</forename>
        <surname>Sinclair</surname>
    </persName>
    
    <note type="dates"><date>1794–1861</date></note>
    <sex value="M"/>
    <note type="biography">
        <p>Scottish surgeon, naturalist, and colonial administrator. Assistant surgeon, Royal Navy, 1822–32; surgeon, 1835–43. Collected botanical and zoological specimens for the British Museum and Royal Botanic Gardens, Kew. Settled in New Zealand, 1843; colonial secretary, 1844–56; became a member of the legislative council in 1844. Elected a fellow of the Linnean Society, 1857. In 1858, began collecting material for Joseph Dalton Hooker’s <hi rend="italic">Handbook of the New Zealand flora</hi> (J. D. Hooker 1864–7). Drowned on Julius von Haast’s geological surveying expedition to the headwaters of the Rangitata river, Canterbury province.</p></note>
    <note type="sources">
        <p><ref target="../bibliographies/bibl_2064.xml" resp="#mjhawkins"><hi rend="italic">DNZB</hi></ref>.</p>
    </note>
    <note type="volume">3,7,9,10,30</note>
    <note type="keywords">
        <term type="society">fellow</term>
        <term type="name">Hooker, J. D.</term>
        <term type="name">Haast, J. F. J. von</term>
        <term type="flora">flora</term>
        <term type="societal">Royal Navy</term>
        <term type="societal">British Museum</term>
        <term type="societal">Royal Botanic Gardens</term>
        <term type="societal">legislative council</term>
        <term type="societal">Linnean Society</term>
        <term type="place">Kew</term>
        <term type="place">New Zealand</term>
        <term type="place">Rangitata river</term>
        <term type="place">Canterbury province</term>
        <term type="reference">Handbook of the New Zealand flora </term>
        <term type="nationality">Scottish</term>
        <term type="h">surgeon</term>
        <term type="a">naturalist</term>
        <term type="p">colonial administrator</term>
    </note>
</person>