<?xml version="1.0" encoding="UTF-8"?>
<?xml-model href="../schema/identified-entities.rng" type="application/xml" schematypens="http://relaxng.org/ns/structure/1.0"?>
<person xmlns="http://www.tei-c.org/ns/1.0" xml:id="DCP-IDENT-363" status="released">
    <persName>
        <forename>Joseph</forename>
        <forename>Georg</forename>
        <surname>Beer</surname>
    </persName>
    
    <note type="dates"><date>1803–73</date></note>
    <sex value="M"/>
    <note type="biography">
        <p>Austrian botanist. Worked in the family clothing business until 1843, when he began to devote himself to botany full time. Studied orchids and bromeliads and later the cultivation of fruit trees. General secretary of the kaiserlich-königliche Gartenbau-Gesellschaft of Vienna, 1859–66. Government representative to horticultural exhibitions in Paris, 1867, and Hamburg, 1869. Member of the government committee for the world horticultural exhibition in Vienna, 1873.</p></note>
    <note type="sources">
        <p><ref target="../bibliographies/bibl_25.xml" resp="#mjhawkins"><hi rend="italic">ADB</hi></ref>.</p>
    </note>
    <note type="volume">12</note>
    <note type="keywords">
        <term type="societal">kaiserlich-königliche Gartenbau-Gesellschaft </term>
        <term type="societal">horticultural exhibitions</term>
        <term type="societal">world horticultural exhibition </term>
        <term type="flora">orchids</term>
        <term type="flora">bromeliads</term>
        <term type="flora">fruit trees</term>
        <term type="place">Vienna</term>
        <term type="place">Paris</term>
        <term type="place">Hamburg</term>
        <term type="nationality">Austrian</term>
        <term type="a">botanist</term>
    </note>
</person>