<?xml version="1.0" encoding="UTF-8"?>
<?xml-model href="../schema/identified-entities.rng" type="application/xml" schematypens="http://relaxng.org/ns/structure/1.0"?>
<person xmlns="http://www.tei-c.org/ns/1.0" xml:id="DCP-IDENT-2" status="released">
    <persName>
        <surname>Ponderer</surname>
    </persName>
    
    <note type="dates"><date>fl. 1860s</date></note>
    
    <note type="biography">
        <p>Pseudonymous letter-writer to the <hi rend="italic">Athenæum.</hi></p></note> 
    <note type="volume">17</note>
    <note type="keywords">
        <term type="reference">Athenæum</term>
        <term type="occupation">Writer</term>
    </note>
</person>