<?xml version="1.0" encoding="UTF-8"?>
<?xml-model href="../schema/identified-entities.rng" type="application/xml" schematypens="http://relaxng.org/ns/structure/1.0"?>
<person xmlns="http://www.tei-c.org/ns/1.0" xml:id="DCP-IDENT-2404" status="released">
    <persName>
        <forename>Beaumont</forename>
        <surname>Hotham</surname>
    </persName>
    <persName type="additional" subtype="title">3d Baron Hotham</persName>
    
    <note type="dates"><date>1794–1870</date></note>
    <sex value="M"/>
    <note type="biography">
        <p>Army officer. Tory MP for Leominster, 1820–41; East Riding, Yorkshire, 1841–68.</p></note>
    <note type="sources">
        <p><ref target="../bibliographies/bibl_2063.xml" resp="#mjhawkins"><hi rend="italic">DNB</hi></ref>.</p>
    </note>
    <note type="volume">6</note>
    <note type="keywords">
        <term type="place">Leominster</term>
        <term type="place">East Riding</term>
        <term type="place">Yorkshire</term>
        <term type="m">Army officer</term>
    </note>
</person>