<?xml version="1.0" encoding="UTF-8"?>
<?xml-model href="../schema/identified-entities.rng" type="application/xml" schematypens="http://relaxng.org/ns/structure/1.0"?>
<person xmlns="http://www.tei-c.org/ns/1.0" xml:id="DCP-IDENT-8327" status="released">
   <persName>
        <forename>Charles</forename>
        <surname>Magniac</surname>
    </persName>
   
   <note type="dates"><date>1827–91</date></note>
   <sex value="M"/>
   <note type="biography">
      <p>Politician. Educated at Trinity College, Cambridge. MP for St Ives, Cornwall, 1868–74; for Bedford, 1880–5 and 1885–6. Partner in the firm of Matheson and Co., East India and China merchants. First president of the London Chamber of Commerce, 1882.</p></note>
   <note type="sources">
      <p><ref target="../bibliographies/bibl_144.xml" resp="#mjhawkins"><hi rend="italic">Alum. Cantab</hi></ref>.</p>
   </note>
   <note type="volume">30</note>
   <note type="keywords">
      <term type="p">politician</term>
   </note>
   
</person>