<?xml version="1.0" encoding="UTF-8"?>
<?xml-model href="../schema/identified-entities.rng" type="application/xml" schematypens="http://relaxng.org/ns/structure/1.0"?>
<person xmlns="http://www.tei-c.org/ns/1.0" xml:id="DCP-IDENT-8475" status="released">
    <persName>
        <forename>William</forename>
        <forename>Llewellyn</forename>
        <surname>Hacon</surname>
    </persName>
    
    <note type="dates"><date>1860–1910</date></note>
    <sex value="M"/>
    <note type="biography">
        <p>Barrister. Eldest son of William Mackmurdo Hacon. Educated at Balliol College, Oxford, and Lincoln’s Inn. Called to the bar, 1885. In 1896, with the designer Charles de Sousy Ricketts, set up Vale Press, which published fine editions, including <hi rend="italic">The Vale Shakespeare</hi>. 
        </p></note>
    <note type="sources"> 
        <p><ref target="../bibliographies/bibl_5374.xml" resp="#mjhawkins"><hi rend="italic">Men-at-the-bar</hi></ref></p>
        <p><ref target="../bibliographies/bibl_5933.xml" resp="#mjhawkins"><hi rend="italic">ODNB</hi></ref> s.v. Ricketts, Charles de Sousy</p>
        <p><hi rend="italic">England &amp; Wales, national probate calendar</hi> (<hi rend="italic">index of wills and administrations</hi>), <hi rend="italic">1858–1966, 1973–95</hi> (Ancestry.com, accessed 29 January 2018)</p>
 </note>
    <note type="volume">27</note>
    <note type="keywords">
        <term type="name">Hacon, William Llewellyn</term>
    </note>
    
</person>