<?xml version="1.0" encoding="UTF-8"?>
<?xml-model href="../schema/identified-entities.rng" type="application/xml" schematypens="http://relaxng.org/ns/structure/1.0"?>
<person xmlns="http://www.tei-c.org/ns/1.0" xml:id="DCP-IDENT-6499" status="released">
    <persName>
        <forename>Jean</forename>
        <forename>Baptiste</forename>
        <surname>Payer</surname>
    </persName>
    
    <note type="dates"><date>1818–60</date></note>
    
    <note type="biography">
        <p>French botanist. Professor of geology and mineralogy at Rennes, 1840. Professor of botany at the Ecole Normale, Paris, 1841. Professor of plant organography, Faculté des Sciences, Paris, 1852. Member of the Académie des Sciences, Paris, 1854.</p></note>
    <note type="sources">
        <p><ref target="../bibliographies/bibl_4080.xml" resp="#mjhawkins"><hi rend="italic">IBF</hi></ref>.</p>
    </note>
    <note type="volume">13,17</note>
</person>