<?xml version="1.0" encoding="UTF-8"?>
<?xml-model href="../schema/identified-entities.rng" type="application/xml" schematypens="http://relaxng.org/ns/structure/1.0"?>
<person xmlns="http://www.tei-c.org/ns/1.0" xml:id="DCP-IDENT-9525" status="released">
   <persName>
      <forename>Sophia</forename>
      <forename>Henrietta</forename>
      <choice>
         <seg><surname notBefore="1813" notAfter="1838">Mainwaring</surname></seg>
         <seg><surname notBefore="1838" notAfter="1871">Coyney</surname></seg>
      </choice>
   </persName>
   <note type="dates"><date>1813–71</date></note>
   <sex value="F"/>
   <note type="biography">
      <p>Eldest daughter of Rowland Mainwaring of Whitmore, Staffordshire, and his first wife, Sophia Henrietta Duff. Born in Smyrna (now Izmir), Turkey. Married Charles Coyney of Weston Coyney in 1838.</p></note>
   <note type="sources">
      <p><ref target="../bibliographies/bibl_10724.xml">Cavenagh-Mainwaring [1934]</ref>, p. 108</p>
      <p>Levantine Heritage Foundation, levantineheritage.com/pdf/london.pdf (accessed 14 June 2021)</p>
   </note>
   <note type="volume">30</note>
   <note type="keywords">
      <term type="p">Smyrna</term>
   </note>
   
</person>