<?xml version="1.0" encoding="UTF-8"?>
<?xml-model href="../schema/identified-entities.rng" type="application/xml" schematypens="http://relaxng.org/ns/structure/1.0"?>
<person xmlns="http://www.tei-c.org/ns/1.0" xml:id="DCP-IDENT-4137" status="released">
    <persName>
        <forename>Edward</forename>
        <forename>Caldwell</forename>
        <surname>Rye</surname>
    </persName>
    
    <note type="dates"><date>1832–85</date></note>
    <sex value="M"/>
    <note type="biography">
        <p>Entomologist. Contributed articles on Coleoptera to the <hi rend="italic">Weekly Intelligencer</hi>, the <hi rend="italic">Zoologist</hi>, and the <hi rend="italic">Entomologist’s Annual.</hi> Offered a position on the staff of the <hi rend="italic">Entomologist’s Monthly Magazine</hi>, 1864. Contributed to <hi rend="italic">Zoological Record</hi> from 1870; later became its editor. Elected fellow of the Zoological Society of London, 1874. Librarian of the Royal Geographical Society, 1875–85. Married Isabella Sophia, second daughter of George Robert Waterhouse, in 1867.</p></note>
    <note type="sources">
        <p><ref target="../bibliographies/bibl_5933.xml" resp="#mjhawkins"><hi rend="italic">ODNB</hi></ref></p>
    </note>
    <note type="volume">18,21,24</note>
    <note type="keywords">
        <term type="reference">Zoological Record</term>
        <term type="reference">Field</term>
        <term type="a">Entomologist</term>
        <term type="l">Editor</term>
    </note>
</person>