<?xml version="1.0" encoding="UTF-8"?>
<?xml-model href="../schema/identified-entities.rng" type="application/xml" schematypens="http://relaxng.org/ns/structure/1.0"?>
<person xmlns="http://www.tei-c.org/ns/1.0" xml:id="DCP-IDENT-1715" status="released">
    <persName>
        <forename>Francis</forename>
        <surname>Fox</surname>
    </persName>
    
    <note type="dates"><date>1759–1833</date></note>
    <sex value="M"/>
    <note type="biography">
        <p>Physician in Derby. Performed the post-mortem on Erasmus Darwin (1731–1802).</p></note> 
    <note type="sources">
        <p><hi rend="italic">Derbyshire, England, Church of England burials, 1813–1991</hi> (Ancestry.com, accessed 17 November 2017)</p>
        <p><hi rend="italic">Derbyshire, England, Church of England baptisms, marriages and burials, 1538–1812</hi> (Ancestry.com, accessed 17 November 2017)</p>
        <p><ref target="../bibliographies/bibl_4366.xml" resp="#mjhawkins">King-Hele 1999</ref>, p. 342.</p>
    </note>
    <note type="volume">27</note>
   
    
</person>