<?xml version="1.0" encoding="UTF-8"?>
<?xml-model href="../schema/bibliographies.rng" type="application/xml" schematypens="http://relaxng.org/ns/structure/1.0"?>
<bibl xmlns="http://www.tei-c.org/ns/1.0" xml:id="DCP-BIBL-1650" status="released">
    <bibl>Croll, James. 1866c. On the physical cause of the submergence and emergence of the land during the glacial epoch. With a note by Prof. W. Thomson. <hi rend="italic">Philosophical Magazine</hi> 4th ser. 31: 301–6.</bibl>
    <idno>SF3 P340.1.c.95.146</idno>
    <note type="volume">16</note>
    
</bibl>