<?xml version="1.0" encoding="UTF-8"?>
<?xml-model href="../schema/bibliographies.rng" type="application/xml" schematypens="http://relaxng.org/ns/structure/1.0"?>
<bibl xmlns="http://www.tei-c.org/ns/1.0" xml:id="DCP-BIBL-7432" status="released">
    <bibl><hi rend="italic">Stedman’s medical eponyms</hi>: <hi rend="italic">Stedman’s medical eponyms.</hi> Edited by Pat Forbis and Susan L. Bartolucci. Baltimore and London: Williams &amp; Wilkins. 1998.</bibl>
    <idno>WBB4 2001.9.2478</idno>
    <note type="volume">18</note>
    
</bibl>