<?xml version="1.0" encoding="UTF-8"?>
<?xml-model href="../schema/bibliographies.rng" type="application/xml" schematypens="http://relaxng.org/ns/structure/1.0"?>
<bibl xmlns="http://www.tei-c.org/ns/1.0" xml:id="DCP-BIBL-5165" status="released">
    <bibl>Major, Charles Immanuel Forsyth. 1873. La faune des vertébrés de Monte Bamboli. <hi rend="italic">Atti della Società Italiana di Scienze Naturali</hi> 15 (1872–3): 290–503.</bibl>
    <idno>DAR Pamphlet G899 / CP382.c.133.15</idno>
    <note type="volume">20,30</note>
    
</bibl>