<?xml version="1.0" encoding="UTF-8"?>
<?xml-model href="../schema/bibliographies.rng" type="application/xml" schematypens="http://relaxng.org/ns/structure/1.0"?>
<bibl xmlns="http://www.tei-c.org/ns/1.0" xml:id="DCP-BIBL-11153" status="released">
    <bibl><hi rend="italic">Verslag omtrent het Middelbaar en Lager Onderwijs over 1892</hi>: <hi rend="italic">Algemeen Verslag van het Middelbaar en Lager Onderwijs voor Europeanen en met dezen Gelijkgestelden in Nederlandsch-Indië over 1892</hi>. Batavia: Landsdrukkerij. 1893.</bibl>     
    <idno>https://www.dbnl.org/arch/_alg010189201_01/pag/_alg010189201_01.pdf</idno>
    <note type="volume">28</note>
    
</bibl>