<?xml version="1.0" encoding="UTF-8"?>
<?xml-model href="../schema/bibliographies.rng" type="application/xml" schematypens="http://relaxng.org/ns/structure/1.0"?>
<bibl xmlns="http://www.tei-c.org/ns/1.0" xml:id="DCP-BIBL-10869" status="released">
  <bibl>Vries, Hugo de. 1871. Sur la perméabilité du protoplasma des betteraves rouges. <hi rend="italic">Archives néerlandaises des sciences exactes et naturelles</hi> 6: 117–26.</bibl> 
  <idno>Online:  </idno>
    <note type="volume">27</note>
    
</bibl>