<?xml version="1.0" encoding="UTF-8"?>
<?xml-model href="../schema/bibliographies.rng" type="application/xml" schematypens="http://relaxng.org/ns/structure/1.0"?>
<bibl xmlns="http://www.tei-c.org/ns/1.0" xml:id="DCP-BIBL-1206" status="released">
    <bibl>Candolle, Alphonse de. 1882. Darwin considéré au point de vue des causes de son succès et de l’importance de ses travaux. <hi rend="italic">Bibliothèque Universelle. Archives de Sciences Physiques et Naturelles</hi> ser. 3, 7: 481–95.</bibl>
    <idno>SF3 340:2.c.91.72</idno>
    <note type="volume">11</note>
</bibl>