<?xml version="1.0" encoding="UTF-8"?>
<?xml-model href="../schema/bibliographies.rng" type="application/xml" schematypens="http://relaxng.org/ns/structure/1.0"?>
<bibl xmlns="http://www.tei-c.org/ns/1.0" xml:id="DCP-BIBL-2447" status="released">
    <bibl>Farley, John. 1977. <hi rend="italic">The spontaneous generation controversy from Descartes to Oparin.</hi> Baltimore, Md., and London: Johns Hopkins University Press.</bibl>
    <idno>SF5 379.2.c.95.75</idno>
    <note type="volume">8,10,11,20</note>
</bibl>