<?xml version="1.0" encoding="UTF-8"?>
<?xml-model href="../schema/bibliographies.rng" type="application/xml" schematypens="http://relaxng.org/ns/structure/1.0"?>
<bibl xmlns="http://www.tei-c.org/ns/1.0" xml:id="DCP-BIBL-11274" status="released">
    <bibl>Bernardin de Saint Pierre, Jacques Henri. 1773. <hi rend="italic">Voyage à l’Isle de France, à l’Isle de Bourbon, au Cap de Bonne-Espérance</hi>. 2 vols. Amsterdam and Paris: Merlin.</bibl>
    <idno>RB Gg.29.50-51</idno>
    <note type="volume">28</note>
    
</bibl>