<?xml version="1.0" encoding="UTF-8"?>
<?xml-model href="../schema/bibliographies.rng" type="application/xml" schematypens="http://relaxng.org/ns/structure/1.0"?>
<bibl xmlns="http://www.tei-c.org/ns/1.0" xml:id="DCP-BIBL-7072" status="released">
    <bibl>Sedgwick, Adam. 1835. Remarks on the structure of large mineral masses, and especially on the chemical changes produced in the aggregation of stratified rocks during different periods after their deposition. [Read 11 March 1835.] <hi rend="italic">Transactions of the Geological Society of London</hi> 2d ser. 3: 461–86.</bibl>
    <idno>NF6 Q365.b.12</idno>
    <note type="volume">11</note>
</bibl>