<?xml version="1.0" encoding="UTF-8"?>
<?xml-model href="../schema/bibliographies.rng" type="application/xml" schematypens="http://relaxng.org/ns/structure/1.0"?>
<bibl xmlns="http://www.tei-c.org/ns/1.0" xml:id="DCP-BIBL-10318" status="released">
    <bibl>Buchholz, Reinhold Wilhelm. 1874. Crustaceen. In <hi rend="italic">Die zweite deutsche Nordpolarfahrt in den Jahren 1869 und 1870 unter Führung des Kapitän Karl Koldewey</hi> vol. 2, Wissenschaftliche Ergebnisse, edited by Verein für die Deutsche Nordpolarfahrt in Bremen. Leipzig: Brockhaus.</bibl>
    <idno>https://archive.org/stream/diezweitedeutsch21kold#page/262/mode/2up</idno>
    <note type="volume">25</note>
    
</bibl>