<?xml version="1.0" encoding="UTF-8"?>
<?xml-model href="../schema/bibliographies.rng" type="application/xml" schematypens="http://relaxng.org/ns/structure/1.0"?>
<bibl xmlns="http://www.tei-c.org/ns/1.0" xml:id="DCP-BIBL-7594" status="released">
    <bibl>Swinhoe, Robert. 1864b. On a new rat from Formosa. [Read 10 May 1864.] <hi rend="italic">Proceedings of the Zoological Society of London</hi> (1864): 185–7. [<hi rend="italic">Annals and Magazine of Natural History</hi> 15 (1865): 71–3.]</bibl>
    <idno>PR (NC) CP384.b.21</idno>
    <note type="volume">18</note>
    
</bibl>