<?xml version="1.0" encoding="UTF-8"?>
<?xml-model href="../schema/bibliographies.rng" type="application/xml" schematypens="http://relaxng.org/ns/structure/1.0"?>
<bibl xmlns="http://www.tei-c.org/ns/1.0" xml:id="DCP-BIBL-10952" status="released">
    <bibl>Humphrey, J. 1946. <hi rend="italic">Story of the Sind Club, 1871–1946.</hi> Karachi: Union Press.</bibl>
    <idno>http://www.sanipanhwar.com/Story%20of%20the%20Sindh%20Club%201871-1946%20by%20J.%20Humphrey.pdf (accessed 18 June 2018)</idno>
    <note type="volume">27</note>
    
    
</bibl>