<?xml version="1.0" encoding="UTF-8"?>
<?xml-model href="../schema/bibliographies.rng" type="application/xml" schematypens="http://relaxng.org/ns/structure/1.0"?>
<bibl xmlns="http://www.tei-c.org/ns/1.0" xml:id="DCP-BIBL-10474" status="released">
    <bibl>Gray, Asa. 1878c. Supplementary note to the review of Darwin’s ‘Forms of flowers’. <hi rend="italic">American Journal of Science and Arts</hi> 3d ser. 15: 221–2.</bibl> 
    <idno>https://archive.org/stream/mobot31753002152939#page/220/mode/2up 
        DAR 133.19: 38 signed 'AG' at the end.</idno>
    <note type="volume">26</note>
    
</bibl>