<?xml version="1.0" encoding="UTF-8"?>
<?xml-model href="../schema/bibliographies.rng" type="application/xml" schematypens="http://relaxng.org/ns/structure/1.0"?>
<bibl xmlns="http://www.tei-c.org/ns/1.0" xml:id="DCP-BIBL-2744" status="released">
    <bibl>Gätke, Heinrich. 1895. <hi rend="italic">Heligoland as an ornithological observatory: the result of fifty years’ experience.</hi> Translated by Rudolph Rosenstock. Edinburgh: David Douglas.</bibl>
    <idno>NC MB.73.54</idno>
    <note type="volume">15</note>
    
</bibl>