<?xml version="1.0" encoding="UTF-8"?>
<?xml-model href="../schema/bibliographies.rng" type="application/xml" schematypens="http://relaxng.org/ns/structure/1.0"?>
<bibl xmlns="http://www.tei-c.org/ns/1.0" xml:id="DCP-BIBL-3752" status="released">
    <bibl>Hooker, Joseph Dalton. 1846a. Description of <hi rend="italic">Pleuropetalum</hi>, a new genus of Portulaceæ, from the Galapago Islands. <hi rend="italic">London Journal of Botany</hi> 5: 108–9.</bibl>
    <idno>NF6 Q370.c.12</idno>
    <note type="volume">8</note>
</bibl>