<?xml version="1.0" encoding="UTF-8"?>
<?xml-model href="../schema/bibliographies.rng" type="application/xml" schematypens="http://relaxng.org/ns/structure/1.0"?>
<bibl xmlns="http://www.tei-c.org/ns/1.0" xml:id="DCP-BIBL-8314" status="released">
    <bibl>Whately, Richard. 1854. <hi rend="italic">On the origin of civilisation. A lecture by his grace the archbishop of Dublin to the Young Men’s Christian Association.</hi> London.</bibl>
    <idno>WB2 Hib.7.854.9</idno>
    <note type="volume">10,19</note>
</bibl>