<?xml version="1.0" encoding="UTF-8"?>
<?xml-model href="../schema/bibliographies.rng" type="application/xml" schematypens="http://relaxng.org/ns/structure/1.0"?>
<bibl xmlns="http://www.tei-c.org/ns/1.0" xml:id="DCP-BIBL-6981" status="released">
    <bibl>Schrenk, Leopold von. 1858. <hi rend="italic">Reisen und Forschungen im Amur-Lande in den Jahren 1854–1856.</hi> 2 vols. St Petersburg: Akademie der Wissenschaften zu St Petersburg.</bibl>
    <idno>Gg.3.87; 2 vols. bound as one</idno>
    <note type="volume">16</note>
    
</bibl>