<?xml version="1.0" encoding="UTF-8"?>
<?xml-model href="../schema/bibliographies.rng" type="application/xml" schematypens="http://relaxng.org/ns/structure/1.0"?>
<bibl xmlns="http://www.tei-c.org/ns/1.0" xml:id="DCP-BIBL-4590" status="released">
    <bibl>Lartet, Edouard. 1862. New researches concerning the co-existence of man with the great fossil mammals, regarded as characteristic of the latest geological period. <hi rend="italic">Natural History Review</hi> n.s. 2: 53–71.</bibl>
    <idno>WBB4 Q382.c.14</idno>
    <note type="volume">18</note>
    
</bibl>