<?xml version="1.0" encoding="UTF-8"?>
<?xml-model href="../schema/bibliographies.rng" type="application/xml" schematypens="http://relaxng.org/ns/structure/1.0"?>
<bibl xmlns="http://www.tei-c.org/ns/1.0" xml:id="DCP-BIBL-7587" status="released">
    <bibl>Swinhoe, Robert. [1863j.] <hi rend="italic">Ornithological ramble in Foochow, in December 1861.</hi> N.p.: n.p. [Reprinted from <hi rend="italic">Ibis</hi> 4 (1862): 253–65.]</bibl>
    <idno>Dar Pam 2811</idno>
    <note type="volume">11</note>
</bibl>