<?xml version="1.0" encoding="UTF-8"?>
<?xml-model href="../schema/bibliographies.rng" type="application/xml" schematypens="http://relaxng.org/ns/structure/1.0"?>
<bibl xmlns="http://www.tei-c.org/ns/1.0" xml:id="DCP-BIBL-4314" status="released">
    <bibl>Keller, Ferdinand. 1866. <hi rend="italic">The lake dwellings of Switzerland and other parts of Europe.</hi> Translated and arranged by John Edward Lee. London: Longmans, Green, and Co.</bibl>
    <idno>WBB Rm 4 Jj.1.37</idno>
    <note type="volume">13</note>
</bibl>