<?xml version="1.0" encoding="UTF-8"?>
<?xml-model href="../schema/bibliographies.rng" type="application/xml" schematypens="http://relaxng.org/ns/structure/1.0"?>
<bibl xmlns="http://www.tei-c.org/ns/1.0" xml:id="DCP-BIBL-9540" status="released">
    <bibl>Lynch, Richard Irwin. 1877. Note on the blimbing (<hi rend="italic">Averrhoa bilimbi</hi>, Linn.). [Read 21 June 1877.] <hi rend="italic">Journal of the Linnean Society</hi> (<hi rend="italic">Botany</hi>) 16: 231–2.</bibl>
    <idno>http://www.biodiversitylibrary.org/item/8368#page/244/mode/1up</idno>
    <note type="volume">25,26</note>
    
</bibl>