<?xml version="1.0" encoding="UTF-8"?>
<?xml-model href="../schema/bibliographies.rng" type="application/xml" schematypens="http://relaxng.org/ns/structure/1.0"?>
<bibl xmlns="http://www.tei-c.org/ns/1.0" xml:id="DCP-BIBL-10053" status="released">
    <bibl>Carpenter, William Benjamin. 1875. <hi rend="italic">The microscope and its revelations.</hi> 5th edition. London: J. and A. Churchill.</bibl>
    <idno>archive.org (https://archive.org/stream/microscopeitsrev1875carp#page/n13/mode/2up)</idno>
    <note type="volume">24</note>
    
</bibl>