<?xml version="1.0" encoding="UTF-8"?>
<?xml-model href="../schema/bibliographies.rng" type="application/xml" schematypens="http://relaxng.org/ns/structure/1.0"?>
<bibl xmlns="http://www.tei-c.org/ns/1.0" xml:id="DCP-BIBL-10715" status="released">
    <bibl>Sauer, Angelika E. 2007. The unbounded German nation: Dr. Otto Hahn and German emigration to Canada in the 1870s and 1880s. <hi rend="italic">Canadian Ethnic Studies</hi> 39: 129–44.</bibl>
    <idno>https://muse.jhu.edu/article/254219</idno>
    <note type="volume">27,28,29,30</note>
    
</bibl>