<?xml version="1.0" encoding="UTF-8"?>
<?xml-model href="../schema/bibliographies.rng" type="application/xml" schematypens="http://relaxng.org/ns/structure/1.0"?>
<bibl xmlns="http://www.tei-c.org/ns/1.0" xml:id="DCP-BIBL-2604" status="released">
    <bibl>Forel, Auguste. 1870. Notices myrmécologiques, I. Sur le Polyergus rufescens. II. Description du Cremastogaster sordidula Nyl. ♂. <hi rend="italic">Mittheilungen der Schweizerische entomologische Gesellschaft</hi> 3: 306–12.</bibl>
    <idno>DAR PAM G884; http://babel.hathitrust.org/cgi/pt?id=uc1.b3993080;view=1up;seq=291</idno>
    <note type="volume">22</note>
    
</bibl>