<?xml version="1.0" encoding="UTF-8"?>
<?xml-model href="../schema/bibliographies.rng" type="application/xml" schematypens="http://relaxng.org/ns/structure/1.0"?>
<bibl xmlns="http://www.tei-c.org/ns/1.0" xml:id="DCP-BIBL-10449" status="released">
    <bibl>Coues, Elliott. 1878. <hi rend="italic">Birds of the Colorado Valley: a repository of scientific and popular information concerning North American ornithology.</hi> Washington: Government Printing Office.</bibl>
    
    <idno> https://archive.org/stream/birdsofcoloradov00coue#page/n8/mode/1up </idno>
   
    <note type="volume">27,30</note>
   
    
</bibl>