<?xml version="1.0" encoding="UTF-8"?>
<?xml-model href="../schema/bibliographies.rng" type="application/xml" schematypens="http://relaxng.org/ns/structure/1.0"?>
<bibl xmlns="http://www.tei-c.org/ns/1.0" xml:id="DCP-BIBL-1984" status="released">
    <bibl>Desmond, Ray. 1992. <hi rend="italic">The European discovery of the Indian flora.</hi> Oxford: Oxford University Press [in association with the] Royal Botanic Gardens.</bibl>
    <idno>SF5 372.4.b.95.67</idno>
    <note type="volume">11,12,13,14,15,16</note>
</bibl>