<?xml version="1.0" encoding="UTF-8"?>
<?xml-model href="../schema/bibliographies.rng" type="application/xml" schematypens="http://relaxng.org/ns/structure/1.0"?>
<bibl xmlns="http://www.tei-c.org/ns/1.0" xml:id="DCP-BIBL-5627" status="released">
    <bibl>Moulinié, Jean Jacques. 1856. <hi rend="italic">De la reproduction chez les trématodes endo-parasites.</hi> Vol. 3 of <hi rend="italic">Memoires de l’Institut National Genevois.</hi> Geneva: Kessman.</bibl>
    <idno>SF4 P340:2.a.6.2(5)</idno>
    <note type="volume">15</note>
    
</bibl>