<?xml version="1.0" encoding="UTF-8"?>
<?xml-model href="../schema/bibliographies.rng" type="application/xml" schematypens="http://relaxng.org/ns/structure/1.0"?>
<bibl xmlns="http://www.tei-c.org/ns/1.0" xml:id="DCP-BIBL-7815" status="released">
    <bibl>Treviranus, Ludolph Christian. 1863a. Ueber Dichogamie nach C. C. Sprengel und Ch. Darwin. <hi rend="italic">Botanische Zeitung</hi>, 2 January 1863, pp. 1–7, 9 January 1863, pp. 9–16.</bibl>
    <idno>WBB rm 4 Q370.b.7.21; DAR Pam Q 80 lightly annotated</idno>
    <note type="volume">10,11,12,13,16,30</note>
</bibl>